Workbook

Sheet 1. Assumptions
B2: Tab 1 — ASSUMPTIONS / Giả định đầu vào
B3: Luật chơi: chỉ điền vào các ô MÀU VÀNG. Các ô khác là công thức và sẽ tự tính.
B5: 1. Product & Pricing / Sản phẩm & Giá
C6: Optimistic | D6: Base | E6: Pessimistic | F6: Đơn vị | G6: Ghi chú / Note
B7: ARPU — Giá bán bình quân/khách/tháng | C7: 2000000 | D7: 800000 | E7: 150000 | F7: VND | G7: Pricing cao hơn → khó bán hơn nhưng margin tốt hơn
B8: Adoption rate — % TAM chuyển thành khách/tháng | C8: 0.021 | D8: 0.0046 | E8: 0.002 | F8: %/tháng | G8: % TAM chuyển thành khách trả tiền mới mỗi tháng
B9: Total addressable market (số khách tiềm năng) | C9: 32500 | D9: 65000 | E9: 130000 | F9: khách | G9: Tổng số khách hàng tiềm năng có thể tiếp cận được
B11: 2. COGS / Chi phí biến đổi trên mỗi khách hàng
B12: API cost / tháng | C12: 0 | D12: 0 | E12: 0 | F12: VND | G12: Tiền gọi OpenAI/Anthropic/Gemini API
B13: Domain và email service / tháng | C13: 0 | D13: 300000 | E13: 500000 | F13: VND
B14: Hidden costs (labeling, retraining, QA) / tháng | C14: 0 | D14: 300000 | E14: 500000 | F14: VND | G14: Đừng quên! Đây là cục giết startup AI
B15: Infrastructure (server/cloud) / tháng | C15: 200000 | D15: 300000 | E15: 500000 | F15: VND | G15: Phần allocate cloud cost cho mỗi khách
B16: → Tổng COGS / khách / tháng | C16: =(C12+C13+C14+C15)/(C9*C8) -> 293.04029 | D16: =(D12+D13+D14+D15)/(D9*D8) -> 3010.0334 | E16: =(E12+E13+E14+E15)/(E9*E8) -> 5769.2308
B18: 3. Customer Behavior / Hành vi khách hàng
B19: Monthly Churn Rate — % khách rời mỗi tháng | C19: 0.05 | D19: 0.08 | E19: 0.12 | F19: % | G19: % user ngưng tương tác với app trong tháng (không mở app, không xem thiết kế, không thêm đồ
B20: Tần suất mua hàng trung bình / tháng | C20: 0.167 | D20: 0.125 | E20: 0.08 | G20: 1 năm mọi người thường đồ nội thất 1 - 2 lần
B21: → Số tháng ở lại trung bình | C21: =IFERROR(1/C19,0) -> 20 | D21: =IFERROR(1/D19,0) -> 12.5 | E21: =IFERROR(1/E19,0) -> 8.3333333
B23: 4. Sales & Marketing / Chi phí thu hút khách
B24: CAC — Tổng chi phí có 1 khách hàng mới | C24: 1 | D24: 4000 | E24: 13750 | F24: VND | G24: Tổng tiền Marketing & Sales / Số khách mới
B26: 5. Fixed Costs / Chi phí cố định hàng tháng
B27: Salaries — Lương team (PM/Dev/Designer) | C27: 20000000 | D27: 30000000 | E27: 40000000 | F27: VND/tháng | G27: Pessimistic = phải hire thêm nếu khó scale
B28: Office, tools, admin | C28: 500000 | D28: 900000 | E28: 1500000 | F28: VND/tháng
B29: Marketing budget hàng tháng | C29: 0 | D29: 1200000 | E29: 2000000 | F29: VND/tháng
B30: → Tổng Fixed Cost / tháng | C30: =SUM(C27:C29) -> 20500000 | D30: =SUM(D27:D29) -> 32100000 | E30: =SUM(E27:E29) -> 43500000
B32: 6. Initial Investment / Vốn đầu tư ban đầu
B33: Vốn đầu tư ban đầu (build MVP, setup) | C33: 10000000 | D33: 20000000 | E33: 30000000 | F33: VND | G33: Chi phí 1 lần — lương team build MVP, infrastructure setup
B34: Tiền mặt ban đầu (sau khi đã trừ vốn đầu tư) | C34: 100000000 | D34: 100000000 | E34: 70000000 | F34: VND | G34: Số tiền có sẵn để chi trả fixed cost trong giai đoạn đầu
B36: 7. Discount Rate / Tỷ suất chiết khấu (cho NPV)
B37: Annual discount rate (WACC) | C37: 0.2 | D37: 0.2 | E37: 0.2 | F37: %/năm | G37: Mức kỳ vọng tối thiểu của nhà đầu tư cho dự án AI rủi ro
B38: → Monthly discount rate | C38: =(1+C37)^(1/12)-1 -> 0.01530947 | D38: =(1+D37)^(1/12)-1 -> 0.01530947 | E38: =(1+E37)^(1/12)-1 -> 0.01530947
B40: 8. Decision Note / Ghi chú quyết định
B41: YourSpace: Ứng dụng cho phép người dùng kéo thả, thêm bớt đồ nội thất từ không gian có sẵn(ảnh chụp), cho phép người dùng thử nghiệm và mua luôn đồ vừa thử nếu muốn
B42: YourSpace cũng là nền tảng marketplace/trung gian (kết nối khách thiết kế nội thất với nhà cung cấp/nhà thầu), thu lợi nhuận dựa trên tỉ lệ phần trăm hoa hồng. 'ARPU = GMV bình quân / khách × Tỷ lệ hoa hồng (%)'.
B43: Thị trường online furniture HCM + HN = ~26,000 tỷ VND/năm → /12 = ~2,167 tỷ VND/tháng Target segment (middle-class, đơn lẻ 1 món) = 30% → 2,167 × 30% = ~650 tỷ VND/tháng GMV/đơn base = 10 triệu (1 món: sofa trung cấp, giường, bàn ăn) → TAM = 650 tỷ / 10 triệu = ~65,000 người/tháng SOM năm 1 vẫn giữ nguyên: ~300 đơn/tháng do dự án đặt kì vọng 5,000–10,000 đơn/24 tháng TAM mới: 65,000 người/tháng Adoption Rate = 300 / 65,000 = 0.46%/tháng ≈ 0.5%/tháng
B52: COGS cả tháng: - API cost=0 vì đây chỉ dùng AI model được train, On-device inference (Depth Anything V2). Zero API call — không gọi OpenAI/Gemin - Infrastructure: App cần một server để: Lưu catalog 3D (file .glb) → user tải về điện thoại, lưu metadata sản phẩm (tên, giá, link mua), phục vụ giao diện web/app. MVP dùng Vercel/Netlify free tier — đủ cho giai đoạn đầu. 300k là dự phòng khi vượt giới hạn free hoặc cần CDN để file 3D load nhanh hơn ở VN. 3D asset curation / tháng = 300,000 VND. Rất xông xênh, còn đâu model thì cứ lấy của bên hợp tác, kiểu gì cũng miễn phí' - Domain 150k, email service 150k - Công thức COGS cho mỗi khách hàng/tháng: COGS cả tháng / (TAM * Adoption Rate).
B61: Chiến lược acquisition của YourSpace: - Organic-first — tận dụng cộng đồng sẵn có (Nghiện Nhà 500K+, TikTok #homedecor). Product visual → dễ viral tự nhiên, tự tạo không gian phòng bằng app rồi đăng bài kiểu đẹp chưa kìa, và viết bài PR, cái này thì tự làm được nên free. - Paid ads chỉ dùng để boost bài đã có tương tác tốt. Dùng Canva pro để thiết kế post cho đẹp, 200k/tháng. - Mời influencer nội thất review, 500k/tháng'. → Tổng ~ 1.200.000 tháng/SOM=4000 VNĐ
B67: 1 PM kiêm founder + 1 DEV + 1 DES=30.000.000/tháng Figma Free/Pro, GitHub, Sentry free, Mixpanel free tầm 900k/tháng

Sheet 2. Unit Economics
B2: Tab 2 — UNIT ECONOMICS / Kinh tế đơn vị
B3: Tự động tính từ Tab 1. Kiểm tra: LTV/CAC > 3 (Base) và CAC Payback < 12 tháng.
B5: Chỉ số | C5: Optimistic | D5: Base | E5: Pessimistic | F5: Đơn vị | G5: Benchmark / Note
B7: Trên mỗi khách hàng / per customer
B8: ARPU / tháng | C8: ='1. Assumptions'!C7 -> 2000000 | D8: ='1. Assumptions'!D7 -> 800000 | E8: ='1. Assumptions'!E7 -> 150000 | F8: VND | G8: Liên kết từ Tab Assumptions
B9: COGS / tháng | C9: ='1. Assumptions'!C16 -> 293.04029 | D9: ='1. Assumptions'!D16 -> 3010.0334 | E9: ='1. Assumptions'!E16 -> 5769.2308 | F9: VND
B10: → Gross Profit / tháng | C10: =C8-C9 -> 1999707 | D10: =D8-D9 -> 796989.97 | E10: =E8-E9 -> 144230.77
B11: → Gross Margin % | C11: =IFERROR(C10/C8,0) -> 0.99985348 | D11: =IFERROR(D10/D8,0) -> 0.99623746 | E11: =IFERROR(E10/E8,0) -> 0.96153846 | G11: AI product target: 40-60%. SaaS truyền thống: 80%+
B13: LTV — Customer Lifetime Value
B14: Số tháng ở lại trung bình | C14: ='1. Assumptions'!C21 -> 20 | D14: ='1. Assumptions'!D21 -> 12.5 | E14: ='1. Assumptions'!E21 -> 8.3333333 | F14: tháng
B15: Tần suất mua trung bình/năm | D15: 1.5 | F15: đơn
B16: → LTV = Gross Profit × Số tháng ở lại x Số đơn mỗi tháng | C16: =C10*C14 -> 39994139 | D16: =D10*D14*(D15/12) -> 1245296.8 | E16: =E10*E14 -> 1201923.1 | G16: Tổng lợi nhuận gộp một khách mang lại trong vòng đời
B18: CAC — Customer Acquisition Cost
B19: CAC — Chi phí thu hút 1 khách | C19: ='1. Assumptions'!C24 -> 1 | D19: ='1. Assumptions'!D24 -> 4000 | E19: ='1. Assumptions'!E24 -> 13750 | F19: VND
B21: Key Ratios / Tỷ lệ then chốt
B22: → LTV / CAC Ratio | C22: =IFERROR(C16/C19,0) -> 39994139 | D22: =IFERROR(D16/D19,0) -> 311.32421 | E22: =IFERROR(E16/E19,0) -> 87.412587 | G22: 🎯 Target > 3.0x (tiêu chuẩn vàng VC)
B23: → CAC Payback Period | C23: =IFERROR(C19/C10,0) -> 5.0007327e-07 | D23: =IFERROR(D19/D10,0) -> 0.0050188838 | E23: =IFERROR(E19/E10,0) -> 0.095333333 | G23: 🎯 Target < 12 tháng (early-stage)
B25: Verdict / Kết luận
B26: Unit Economics Status | C26: =IF(AND(C22>=3,C23<=12),"✓ HEALTHY",IF(OR(C22<1,C23>18),"✗ UNHEALTHY","⚠ WATCH")) -> ✓ HEALTHY | D26: =IF(AND(D22>=3,D23<=12),"✓ HEALTHY",IF(OR(D22<1,D23>18),"✗ UNHEALTHY","⚠ WATCH")) -> ✓ HEALTHY | E26: =IF(AND(E22>=3,E23<=12),"✓ HEALTHY",IF(OR(E22<1,E23>18),"✗ UNHEALTHY","⚠ WATCH")) -> ✓ HEALTHY

Sheet 3. P&L & ROI
B2: Tab 3 — P&L & ROI / 24 tháng
B4: Chọn scenario: | D4: Base | E4: Đổi scenario tại đây để toàn bộ P&L tự cập nhật
B6: Active scenario index: | D6: =MATCH(D4,{"Optimistic","Base","Pessimistic"},0) -> 2
B7: Selected scenario inputs ↓
B8: ARPU / khách / tháng | D8: =CHOOSE($D$6,'1. Assumptions'!C7,'1. Assumptions'!D7,'1. Assumptions'!E7) -> 800000
B9: Adoption rate | D9: =CHOOSE($D$6,'1. Assumptions'!C8,'1. Assumptions'!D8,'1. Assumptions'!E8) -> 0.0046
B10: TAM (số khách tiềm năng) | D10: =CHOOSE($D$6,'1. Assumptions'!C9,'1. Assumptions'!D9,'1. Assumptions'!E9) -> 65000
B11: Total COGS / khách | D11: =CHOOSE($D$6,'1. Assumptions'!C16,'1. Assumptions'!D16,'1. Assumptions'!E16) -> 3010.0334
B12: Monthly Churn Rate | D12: =CHOOSE($D$6,'1. Assumptions'!C19,'1. Assumptions'!D19,'1. Assumptions'!E19) -> 0.08
B13: CAC / khách mới | D13: =CHOOSE($D$6,'1. Assumptions'!C24,'1. Assumptions'!D24,'1. Assumptions'!E24) -> 4000
B14: Fixed Cost / tháng | D14: =CHOOSE($D$6,'1. Assumptions'!C30,'1. Assumptions'!D30,'1. Assumptions'!E30) -> 32100000
B15: Initial Investment | D15: =CHOOSE($D$6,'1. Assumptions'!C33,'1. Assumptions'!D33,'1. Assumptions'!E33) -> 20000000
B16: Initial Cash | D16: =CHOOSE($D$6,'1. Assumptions'!C34,'1. Assumptions'!D34,'1. Assumptions'!E34) -> 100000000
B17: Monthly Discount Rate | D17: =CHOOSE($D$6,'1. Assumptions'!C38,'1. Assumptions'!D38,'1. Assumptions'!E38) -> 0.01530947
B20: P&L Projection — 24 months (VND)
B21: Month | C21: M0 | D21: M1 | E21: M2 | F21: M3 | G21: M4 | H21: M5 | I21: M6 | J21: M7 | K21: M8 | L21: M9 | M21: M10 | N21: M11 | O21: M12 | P21: M13 | Q21: M14 | R21: M15 | S21: M16 | T21: M17 | U21: M18 | V21: M19 | W21: M20 | X21: M21 | Y21: M22 | Z21: M23 | AA21: M24 | AB21: TOTAL
B22: New customers acquired | C22: 0 | D22: =ROUND($D$10*$D$9,0) -> 299 | E22: =ROUND($D$10*$D$9,0) -> 299 | F22: =ROUND($D$10*$D$9,0) -> 299 | G22: =ROUND($D$10*$D$9,0) -> 299 | H22: =ROUND($D$10*$D$9,0) -> 299 | I22: =ROUND($D$10*$D$9,0) -> 299 | J22: =ROUND($D$10*$D$9,0) -> 299 | K22: =ROUND($D$10*$D$9,0) -> 299 | ... AA22: =ROUND($D$10*$D$9,0) -> 299 | AB22: =SUM(D22:AA22) -> 7176
B23: Active customers (end of month) | C23: 0 | D23: =D22 -> 299 | E23: =D23*(1-$D$12)+E22 -> 574.08 | F23: =E23*(1-$D$12)+F22 -> 827.1536 | G23: =F23*(1-$D$12)+G22 -> 1059.9813 | H23: =G23*(1-$D$12)+H22 -> 1274.1828 | I23: =H23*(1-$D$12)+I22 -> 1471.2482 | J23: =I23*(1-$D$12)+J22 -> 1652.5483 | K23: =J23*(1-$D$12)+K22 -> 1819.3445 | L23: =K23*(1-$D$12)+L22 -> 1972.7969 | ... AA23: =Z23*(1-$D$12)+AA22 -> 3232.2701
B25: Revenue | D25: =D23*$D$8 -> 239200000 | E25: =E23*$D$8 -> 4.59264e+08 | F25: =F23*$D$8 -> 661722880 | G25: =G23*$D$8 -> 8.4798505e+08 | H25: =H23*$D$8 -> 1.0193462e+09 | I25: =I23*$D$8 -> 1.1769985e+09 | J25: =J23*$D$8 -> 1.3220387e+09 | K25: =K23*$D$8 -> 1.4554756e+09 | ... AA25: =AA23*$D$8 -> 2.5858161e+09 | AB25: =SUM(D25:AA25) -> 4.2023115e+10
B26: COGS (variable cost) | D26: =D23*$D$11 -> 900000 | E26: =E23*$D$11 -> 1728000 | F26: =F23*$D$11 -> 2489760 | G26: =G23*$D$11 -> 3190579.2 | H26: =H23*$D$11 -> 3835332.9 | I26: =I23*$D$11 -> 4428506.2 | J26: =J23*$D$11 -> 4974225.7 | K26: =K23*$D$11 -> 5476287.7 | ... AA26: =AA23*$D$11 -> 9729241.1 | AB26: =SUM(D26:AA26) -> 1.5811373e+08
B27: Gross Profit | D27: =D25-D26 -> 238300000 | E27: =E25-E26 -> 4.57536e+08 | F27: =F25-F26 -> 659233120 | G27: =G25-G26 -> 8.4479447e+08 | H27: =H25-H26 -> 1.0155109e+09 | I27: =I25-I26 -> 1.17257e+09 | J27: =J25-J26 -> 1.3170644e+09 | K27: =K25-K26 -> 1.4499993e+09 | ... AA27: =AA25-AA26 -> 2.5760868e+09 | AB27: =SUM(D27:AA27) -> 4.1865001e+10
B28: Marketing/Acquisition cost | D28: =D22*$D$13 -> 1196000 | E28: =E22*$D$13 -> 1196000 | F28: =F22*$D$13 -> 1196000 | G28: =G22*$D$13 -> 1196000 | H28: =H22*$D$13 -> 1196000 | I28: =I22*$D$13 -> 1196000 | J28: =J22*$D$13 -> 1196000 | K28: =K22*$D$13 -> 1196000 | ... AA28: =AA22*$D$13 -> 1196000 | AB28: =SUM(D28:AA28) -> 28704000
B29: Fixed cost (salaries + ops) | D29: =$D$14 -> 32100000 | E29: =$D$14 -> 32100000 | F29: =$D$14 -> 32100000 | G29: =$D$14 -> 32100000 | H29: =$D$14 -> 32100000 | I29: =$D$14 -> 32100000 | J29: =$D$14 -> 32100000 | K29: =$D$14 -> 32100000 | ... AA29: =$D$14 -> 32100000 | AB29: =SUM(D29:AA29) -> 770400000
B30: Operating Profit (EBITDA) | D30: =D27-D28-D29 -> 205004000 | E30: =E27-E28-E29 -> 4.2424e+08 | F30: =F27-F28-F29 -> 625937120 | G30: =G27-G28-G29 -> 8.1149847e+08 | H30: =H27-H28-H29 -> 9.8221491e+08 | I30: =I27-I28-I29 -> 1.139274e+09 | J30: =J27-J28-J29 -> 1.2837684e+09 | K30: =K27-K28-K29 -> 1.4167033e+09 | ... AA30: =AA27-AA28-AA29 -> 2.5427908e+09 | AB30: =SUM(D30:AA30) -> 4.1065897e+10
B32: Cash Flow (after investment) | C32: -2000000 | D32: =D30-$D$15 -> 185004000 | E32: =E30 -> 4.2424e+08 | F32: =F30 -> 625937120 | G32: =G30 -> 8.1149847e+08 | H32: =H30 -> 9.8221491e+08 | I32: =I30 -> 1.139274e+09 | J32: =J30 -> 1.2837684e+09 | K32: =K30 -> 1.4167033e+09 | L32: =L30 -> 1.5390033e+09 | ... AA32: =AA30 -> 2.5427908e+09 | AB32: =SUM(D32:AA32) -> 4.1045897e+10
B33: Cash Position (cumulative) | D33: =$D$16+D32 -> 285004000 | E33: =D33+E32 -> 709244000 | F33: =E33+F32 -> 1335181120 | G33: =F33+G32 -> 2.1466796e+09 | H33: =G33+H32 -> 3.1288945e+09 | I33: =H33+I32 -> 4.2681685e+09 | J33: =I33+J32 -> 5.551937e+09 | K33: =J33+K32 -> 6.9686403e+09 | L33: =K33+L32 -> 8.5076436e+09 | ... AA33: =Z33+AA32 -> 4.1145897e+10
B36: ROI Metrics / Chỉ số đánh giá tổng thể dự án
B37: NPV (Net Present Value, mil VND) | D37: =(NPV($D$17,E32:AA32)+D32)/1000000 -> 33214.257 | E37: ="(target: > 0)" -> (target: > 0)
B38: IRR (Annual) | D38: =IFERROR((1+IRR(C32:AA32))^12-1,0) -> 5.2523139e+23 | E38: ="(target: > "&TEXT(CHOOSE($D$6,'1. Assumptions'!C37,'1. Assumptions'!D37,'1. Assumptions'!E37),"0.0%")&")" -> (target: > 20.0%)
B39: Project Payback (months) | D39: =IFERROR(MATCH(TRUE(),INDEX(D41:AA41>=0,0),0),"> 24") -> 1 | E39: ="(target: < 24)" -> (target: < 24)
B40: Runway (months until cash = 0) | D40: =IFERROR(MATCH(TRUE(),INDEX(D33:AA33<0,0),0)-1,">= 24") -> >= 24 | E40: ="(target: >= 12)" -> (target: >= 12)
B41: (helper: cumulative cash flow) | D41: =D32 -> 185004000 | E41: =D41+E32 -> 609244000 | F41: =E41+F32 -> 1235181120 | G41: =F41+G32 -> 2.0466796e+09 | H41: =G41+H32 -> 3.0288945e+09 | I41: =H41+I32 -> 4.1681685e+09 | J41: =I41+J32 -> 5.451937e+09 | K41: =J41+K32 -> 6.8686403e+09 | L41: =K41+L32 -> 8.4076436e+09 | ... AA41: =Z41+AA32 -> 4.1045897e+10
B43: Final Verdict / Có nên làm dự án này?
B44: Project Decision | D44: =IF(AND(D37>0,D38>CHOOSE($D$6,'1. Assumptions'!C37,'1. Assumptions'!D37,'1. Assumptions'!E37)),"✓ GO — NPV+ và IRR > WACC",IF(D37<0,"✗ NO-GO — NPV âm: dự án không tạo giá trị","⚠ HOLD — IRR thấp hơn kỳ vọng, cần điều chỉnh")) -> ✓ GO — NPV+ và IRR > WACC
